django_data_loader/__init__.py
django_data_loader-0.2.0.dist-info/METADATA
django_data_loader-0.2.0.dist-info/WHEEL
django_data_loader-0.2.0.dist-info/RECORD
